simbind/__main__.py
simbind/architect/requirements.txt
simbind/architect/simbind_architect/Collector.py
simbind/architect/simbind_architect/Driver.py
simbind/architect/simbind_architect/__init__.py
simbind/architect/simbind_architect/architect_utils.py
simbind/architect/simbind_architect/utils.py
simbind/architect/simbind_architect/mock/MockDriver.py
simbind/architect/simbind_architect/mock/__init__.py
simbind/architect/simbind_architect/mock/templates/BaseModel.py.j2
simbind/architect/simbind_architect/mock/templates/Model.py.j2
simbind/architect/simbind_architect/mock/templates/README.md.j2
simbind/architect/simbind_architect/mock/templates/__init__.py.j2
simbind/architect/simbind_architect/mock/templates/pyproject.toml.j2
simbind/architect/simbind_architect/nodes/Collection.py
simbind/architect/simbind_architect/nodes/FunctionNode.py
simbind/architect/simbind_architect/nodes/FunctionNodeCollection.py
simbind/architect/simbind_architect/nodes/FunctionNodeParameter.py
simbind/architect/simbind_architect/nodes/Node.py
simbind/architect/simbind_architect/nodes/StructNode.py
simbind/architect/simbind_architect/nodes/StructNodeCollection.py
simbind/architect/simbind_architect/nodes/StructNodeMember.py
simbind/architect/simbind_architect/nodes/TypeNodeMap.py
simbind/architect/simbind_architect/nodes/VariableNode.py
simbind/architect/simbind_architect/nodes/VariableNodeCollection.py
simbind/architect/simbind_architect/nodes/__init__.py
simbind/architect/simbind_architect/sil/SiLDriver.py
simbind/architect/simbind_architect/sil/__init__.py
simbind/architect/simbind_architect/sil/templates/BaseModel.py.j2
simbind/architect/simbind_architect/sil/templates/CMakeLists.txt.j2
simbind/architect/simbind_architect/sil/templates/Model.py.j2
simbind/architect/simbind_architect/sil/templates/README.md.j2
simbind/architect/simbind_architect/sil/templates/__init__.py.j2
simbind/architect/simbind_architect/sil/templates/pyproject.toml.j2
simbind-0.2.0.dist-info/LICENSE
simbind-0.2.0.dist-info/METADATA
simbind-0.2.0.dist-info/WHEEL
simbind-0.2.0.dist-info/entry_points.txt
simbind-0.2.0.dist-info/top_level.txt
simbind-0.2.0.dist-info/RECORD
