Metadata-Version: 2.1
Name: simbind
Version: 0.2.0
Summary: Generate Python wheel package from Simulink model!
Author-email: SWAG Engineering UG <contact@swag-engineering.io>
License: GNU AFFERO GENERAL PUBLIC LICENSE
Project-URL: Documentation, https://github.com/swag-engineering/simbind-cli/wiki/Motivation
Project-URL: Repository, https://github.com/swag-engineering/simbind-cli.git
Classifier: Environment :: Console
Classifier: Intended Audience :: Developers
Classifier: Topic :: Software Development :: Build Tools
Classifier: Topic :: Software Development :: Code Generators
Classifier: Topic :: Software Development :: Testing
Classifier: Topic :: Scientific/Engineering :: Mathematics
Classifier: License :: OSI Approved :: GNU Affero General Public License v3
Classifier: Programming Language :: Python
Classifier: Programming Language :: Python :: 3.10
Classifier: Programming Language :: Python :: 3.11
Requires-Python: <3.12,>=3.10
License-File: LICENSE
Requires-Dist: jinja2==3.1.4
Requires-Dist: pycparser==2.22
Requires-Dist: pycparser-fake-libc
Requires-Dist: matlabengine==9.15.2
